threads_dlp/__init__.py
threads_dlp/__version__.py
threads_dlp/cli.py
threads_dlp/downloader.py
threads_dlp/extractor.py
threads_dlp/make_out_path.py
threads_dlp-1.0.3.dist-info/licenses/LICENSE
threads_dlp-1.0.3.dist-info/METADATA
threads_dlp-1.0.3.dist-info/WHEEL
threads_dlp-1.0.3.dist-info/entry_points.txt
threads_dlp-1.0.3.dist-info/top_level.txt
threads_dlp-1.0.3.dist-info/RECORD
