Metadata-Version: 2.4
Name: threads-dlp
Version: 1.0.3
Summary: CLI open-source pour télécharger des vidéos depuis Threads (Meta)
Home-page: https://github.com/nanaelie/threads-dlp
Author: nae.dev
Author-email: naedev <nae.devp@gmail.com>
License: Apache-2.0
Project-URL: Source, https://github.com/nanaelie/threads-dlp
Keywords: threads,pypi,utils,utility,download,video,cli,python,nana,elie,nae,naedev,naedevp,nae.dev,nae.devp
Classifier: Programming Language :: Python :: 3
Classifier: License :: OSI Approved :: Apache Software License
Classifier: Operating System :: OS Independent
Classifier: Environment :: Console
Classifier: Topic :: Multimedia :: Video
Classifier: Intended Audience :: Developers
Requires-Python: >=3.7
License-File: LICENSE
Requires-Dist: requests
Requires-Dist: selenium
Requires-Dist: tqdm
Requires-Dist: dottify>=1.1.1
Dynamic: author
Dynamic: home-page
Dynamic: license-file
Dynamic: requires-python
